README.md
setup.cfg
setup.py
deeplens/__init__.py
deeplens/deeplens.py
deeplens.egg-info/PKG-INFO
deeplens.egg-info/SOURCES.txt
deeplens.egg-info/dependency_links.txt
deeplens.egg-info/top_level.txt